melter/__init__.py
melter/main.py
melter/start_reruns.py
melter/triggers.py
melter/utils.py
melter-0.7.0.dist-info/entry_points.txt
melter-0.7.0.dist-info/LICENSE
melter-0.7.0.dist-info/WHEEL
melter-0.7.0.dist-info/METADATA
melter-0.7.0.dist-info/RECORD
