Metadata-Version: 2.1
Name: melter
Version: 0.7.0
Summary: Identifies unsolved cases that should be analyzed again
Author: Henning Onsbring
Author-email: henning.onsbring@scilifelab.se
Requires-Python: >=3.9,<4.0
Classifier: Programming Language :: Python :: 3
Classifier: Programming Language :: Python :: 3.10
Classifier: Programming Language :: Python :: 3.9
Requires-Dist: requests (>=2.27.1,<3.0.0)
Requires-Dist: typer[all] (>=0.4.0,<0.5.0)
